linux_capabilities/__init__.py
linux_capabilities/__main__.py
py_linux_capabilities-0.1.2.dist-info/LICENSE
py_linux_capabilities-0.1.2.dist-info/METADATA
py_linux_capabilities-0.1.2.dist-info/WHEEL
py_linux_capabilities-0.1.2.dist-info/top_level.txt
py_linux_capabilities-0.1.2.dist-info/RECORD
