Metadata-Version: 2.1
Name: py-linux-capabilities
Version: 0.1.2
Summary: A Python library providing an enumeration of Linux capabilities.
Home-page: https://github.com/damwiw/py-linux-capabilities
Author: damwiw
License: MIT
Project-URL: Homepage, https://github.com/damwiw/py-linux-capabilities
Classifier: Programming Language :: Python :: 3
Classifier: License :: OSI Approved :: MIT License
Classifier: Operating System :: POSIX :: Linux
Requires-Python: >=3.7
License-File: LICENSE
